shortnr/__init__.py
shortnr/admin.py
shortnr/apps.py
shortnr/core.py
shortnr/models.py
shortnr/tests.py
shortnr/utils.py
dj_shortnr-0.1.0.dist-info/LICENCE
dj_shortnr-0.1.0.dist-info/METADATA
dj_shortnr-0.1.0.dist-info/WHEEL
dj_shortnr-0.1.0.dist-info/top_level.txt
dj_shortnr-0.1.0.dist-info/RECORD
